MANIFEST.in
README.rst
setup.py
docs/HISTORY.txt
docs/LICENSE.GPL
docs/LICENSE.rst
rapido/__init__.py
rapido.core.egg-info/PKG-INFO
rapido.core.egg-info/SOURCES.txt
rapido.core.egg-info/dependency_links.txt
rapido.core.egg-info/entry_points.txt
rapido.core.egg-info/namespace_packages.txt
rapido.core.egg-info/not-zip-safe
rapido.core.egg-info/requires.txt
rapido.core.egg-info/top_level.txt
rapido/core/__init__.py
rapido/core/app.py
rapido/core/block.py
rapido/core/configure.zcml
rapido/core/display.py
rapido/core/exceptions.py
rapido/core/formula.py
rapido/core/index.py
rapido/core/interfaces.py
rapido/core/record.py
rapido/core/rest.py
rapido/core/security.py
rapido/core/elements/__init__.py
rapido/core/elements/elements.py
rapido/core/tests/__init__.py
rapido/core/tests/base.py
rapido/core/tests/configure.zcml
rapido/core/tests/test_app.py
rapido/core/tests/test_block.py
rapido/core/tests/test_http.py
rapido/core/tests/test_record.py
rapido/core/tests/test_rest.py