Metadata-Version: 1.1
Name: rapido.core
Version: 1.0.6
Summary: Rapid application builder
Home-page: https://github.com/collective/rapido.core
Author: Eric BREHAULT
Author-email: ebrehault@gmail.com
License: GPL
Keywords: rapido
Platform: UNKNOWN
Classifier: Programming Language :: Python
